phlow/__init__.py
phlow/audit.py
phlow/circuit_breaker.py
phlow/distributed_rate_limiter.py
phlow/exceptions.py
phlow/middleware.py
phlow/rate_limiter.py
phlow/supabase_helpers.py
phlow/types.py
phlow/integrations/__init__.py
phlow/integrations/fastapi.py
phlow/monitoring/__init__.py
phlow/monitoring/logger.py
phlow/monitoring/metrics.py
phlow/rbac/__init__.py
phlow/rbac/cache.py
phlow/rbac/store.py
phlow/rbac/types.py
phlow/rbac/verifier.py
phlow/security/__init__.py
phlow/security/key_management.py
phlow-0.1.9.dist-info/METADATA
phlow-0.1.9.dist-info/WHEEL
phlow-0.1.9.dist-info/RECORD
