Metadata-Version: 2.4
Name: phlow
Version: 0.1.9
Summary: Simple Python library for Phlow authentication
Project-URL: Documentation, https://prassanna.io/phlow/
Project-URL: Issues, https://github.com/prassanna-ravishankar/phlow/issues
Project-URL: Source, https://github.com/prassanna-ravishankar/phlow
Author: Prassanna Ravishankar
License-Expression: MIT
Keywords: a2a,agent,authentication,jwt,middleware,phlow,supabase
Classifier: Development Status :: 4 - Beta
Classifier: Intended Audience :: Developers
Classifier: License :: OSI Approved :: MIT License
Classifier: Programming Language :: Python :: 3
Classifier: Programming Language :: Python :: 3.10
Classifier: Programming Language :: Python :: 3.11
Classifier: Programming Language :: Python :: 3.12
Classifier: Topic :: Software Development :: Libraries :: Python Modules
Requires-Python: >=3.10
Requires-Dist: a2a-sdk>=0.2.11
Requires-Dist: base58>=2.1.1
Requires-Dist: cryptography>=41.0.0
Requires-Dist: httpx>=0.24.0
Requires-Dist: pydantic>=2.0.0
Requires-Dist: pyjwt>=2.8.0
Requires-Dist: supabase>=2.0.0
Requires-Dist: typing-extensions>=4.0.0
Provides-Extra: examples
Requires-Dist: fastapi>=0.100.0; extra == 'examples'
Requires-Dist: python-dotenv>=1.0.0; extra == 'examples'
Requires-Dist: requests>=2.31.0; extra == 'examples'
Requires-Dist: uvicorn[standard]>=0.23.0; extra == 'examples'
Provides-Extra: fastapi
Requires-Dist: fastapi>=0.100.0; extra == 'fastapi'
Provides-Extra: monitoring
Requires-Dist: prometheus-client>=0.20.0; extra == 'monitoring'
Requires-Dist: structlog>=24.1.0; extra == 'monitoring'
Provides-Extra: rbac
Requires-Dist: pyld>=2.0.0; extra == 'rbac'
Provides-Extra: redis
Requires-Dist: redis>=5.0.0; extra == 'redis'
